[
  {
    "id": 1,
    "order_id": "an1001",
    "user": {
      "name": "Alex Shoi",
      "profile_pic": "https://images.unsplash.com/photo-1603415526960-f7e0328c63b1?ixlib=rb-1.2.1&ixid=MnwxMjA3fDB8MHxwaG90by1wYWdlfHx8fGVufDB8fHx8&auto=format&fit=crop&w=1470&q=80"
    },
    "product": "Furniture",
    "price": 3523,
    "vendor": "iTest Factory",
    "payment": "Paid",
    "rating": 5,
    "vote": 54
  },
  {
    "id": 2,
    "order_id": "an1002",
    "user": {
      "name": "Jhon Doe",
      "profile_pic": "https://images.unsplash.com/photo-1507003211169-0a1dd7228f2d?ixlib=rb-1.2.1&ixid=MnwxMjA3fDB8MHxwaG90by1wYWdlfHx8fGVufDB8fHx8&auto=format&fit=crop&w=687&q=80"
    },
    "product": "Grocery",
    "price": 6323,
    "vendor": "Fress Store",
    "payment": "Unpaid",
    "rating": 4.5,
    "vote": 64
  },
  {
    "id": 3,
    "order_id": "an1003",
    "user": {
      "name": "Mr. Mark",
      "profile_pic": "https://images.unsplash.com/photo-1500648767791-00dcc994a43e?ixlib=rb-1.2.1&ixid=MnwxMjA3fDB8MHxwaG90by1wYWdlfHx8fGVufDB8fHx8&auto=format&fit=crop&w=687&q=80"
    },
    "product": "Shoe Store",
    "price": 3523,
    "vendor": "Bata Shoe",
    "payment": "Pending",
    "rating": 4,
    "vote": 21
  },
  {
    "id": 4,
    "order_id": "an1004",
    "user": {
      "name": "Rich Done",
      "profile_pic": "https://images.unsplash.com/photo-1463453091185-61582044d556?ixlib=rb-1.2.1&ixid=MnwxMjA3fDB8MHxwaG90by1wYWdlfHx8fGVufDB8fHx8&auto=format&fit=crop&w=1470&q=80"
    },
    "product": "Book Shop",
    "price": 7389,
    "vendor": "iTest Factory",
    "payment": "Paid",
    "rating": 4.4,
    "vote": 52
  },
  {
    "id": 5,
    "order_id": "an1005",
    "user": {
      "name": "Kark Dip",
      "profile_pic": "https://images.unsplash.com/photo-1629467057571-42d22d8f0cbd?ixlib=rb-1.2.1&ixid=MnwxMjA3fDB8MHxwaG90by1wYWdlfHx8fGVufDB8fHx8&auto=format&fit=crop&w=698&q=80"
    },
    "product": "Furniture",
    "price": 7423,
    "vendor": "Roal Shop",
    "payment": "Paid",
    "rating": 5,
    "vote": 34
  },
  {
    "id": 6,
    "order_id": "an1006",
    "user": {
      "name": "Rock Shirp",
      "profile_pic": "https://images.unsplash.com/photo-1544723795-3fb6469f5b39?ixlib=rb-1.2.1&ixid=MnwxMjA3fDB8MHxwaG90by1wYWdlfHx8fGVufDB8fHx8&auto=format&fit=crop&w=689&q=80"
    },
    "product": "Furniture",
    "price": 3523,
    "vendor": "iTest Factory",
    "payment": "Paid",
    "rating": 5,
    "vote": 54
  },
  {
    "id": 7,
    "order_id": "an1007",
    "user": {
      "name": "Mr. Rechad",
      "profile_pic": "https://images.unsplash.com/photo-1544435253-f0ead49638fa?ixlib=rb-1.2.1&ixid=MnwxMjA3fDB8MHxwaG90by1wYWdlfHx8fGVufDB8fHx8&auto=format&fit=crop&w=687&q=80"
    },
    "product": "Furniture",
    "price": 3523,
    "vendor": "iTest Factory",
    "payment": "Paid",
    "rating": 5,
    "vote": 54
  },
  {
    "id": 8,
    "order_id": "an1008",
    "user": {
      "name": "Eles Xiop",
      "profile_pic": "https://images.unsplash.com/photo-1518806118471-f28b20a1d79d?ixlib=rb-1.2.1&ixid=MnwxMjA3fDB8MHxwaG90by1wYWdlfHx8fGVufDB8fHx8&auto=format&fit=crop&w=764&q=80"
    },
    "product": "Furniture",
    "price": 3523,
    "vendor": "iTest Factory",
    "payment": "Paid",
    "rating": 5,
    "vote": 54
  },
  {
    "id": 9,
    "order_id": "an1009",
    "user": {
      "name": "Mr. Barden",
      "profile_pic": "https://images.unsplash.com/photo-1543610892-0b1f7e6d8ac1?ixlib=rb-1.2.1&ixid=MnwxMjA3fDB8MHxwaG90by1wYWdlfHx8fGVufDB8fHx8&auto=format&fit=crop&w=687&q=80"
    },
    "product": "Furniture",
    "price": 3523,
    "vendor": "iTest Factory",
    "payment": "Paid",
    "rating": 5,
    "vote": 54
  },
  {
    "id": 10,
    "order_id": "an10010",
    "user": {
      "name": "Joi Baiden",
      "profile_pic": "https://images.unsplash.com/photo-1624561172888-ac93c696e10c?ixlib=rb-1.2.1&ixid=MnwxMjA3fDB8MHxwaG90by1wYWdlfHx8fGVufDB8fHx8&auto=format&fit=crop&w=689&q=80"
    },
    "product": "Furniture",
    "price": 3523,
    "vendor": "iTest Factory",
    "payment": "Paid",
    "rating": 5,
    "vote": 54
  }
]
